__init__.py
mobly_android_partner_tools-1.4.2.dist-info/licenses/LICENSE
mobly_runner/__init__.py
mobly_runner/mobly_runner.py
mobly_runner/report_generator.py
results_uploader/__init__.py
results_uploader/mobly_result_converter.py
results_uploader/results_uploader.py
results_uploader/resultstore_client.py
results_uploader/data/mime.types
mobly_android_partner_tools-1.4.2.dist-info/METADATA
mobly_android_partner_tools-1.4.2.dist-info/WHEEL
mobly_android_partner_tools-1.4.2.dist-info/entry_points.txt
mobly_android_partner_tools-1.4.2.dist-info/top_level.txt
mobly_android_partner_tools-1.4.2.dist-info/RECORD
