Metadata-Version: 2.4
Name: mobly-android-partner-tools
Version: 1.4.2
Summary: Command-line utilities used by Android partners to run packaged Mobly tests and upload test results.
Requires-Python: >=3.11
License-File: LICENSE
Requires-Dist: google-api-python-client
Requires-Dist: google-auth
Requires-Dist: google-auth-httplib2
Requires-Dist: google-cloud
Requires-Dist: google-cloud-api-keys
Requires-Dist: google-cloud-resource-manager
Requires-Dist: google-cloud-storage
Requires-Dist: httplib2
Requires-Dist: mobly
Requires-Dist: pipdeptree
Requires-Dist: pyyaml
Dynamic: license-file
